ttnet/__init__.py
ttnet/help.py
ttnet/metrics.py
ttnet/net.py
ttnet/operations.py
ttnet-0.1.10.dist-info/LICENSE
ttnet-0.1.10.dist-info/METADATA
ttnet-0.1.10.dist-info/WHEEL
ttnet-0.1.10.dist-info/RECORD
