Metadata-Version: 2.1
Name: ttnet
Version: 0.1.10
Summary: 
License: MIT
Author: Davide Vega D'Aurelio
Author-email: dvladek@gmail.com
Requires-Python: >=3.10,<4.0
Classifier: License :: OSI Approved :: MIT License
Classifier: Programming Language :: Python :: 3
Classifier: Programming Language :: Python :: 3.10
Classifier: Programming Language :: Python :: 3.11
Classifier: Programming Language :: Python :: 3.12
Requires-Dist: networkx (>=3.2.1,<4.0.0)
Requires-Dist: pandas (>=2.1.3,<3.0.0)
Requires-Dist: result (>=0.14.0,<0.15.0)
Requires-Dist: uunet (==2.1)
